README.md
setup.py
wsblib/__init__.py
wsblib/errors.py
wsblib/exceptions.py
wsblib/log.py
wsblib/request.py
wsblib/route.py
wsblib/server.py
wsblib/status.py
wsblib.egg-info/PKG-INFO
wsblib.egg-info/SOURCES.txt
wsblib.egg-info/dependency_links.txt
wsblib.egg-info/requires.txt
wsblib.egg-info/top_level.txt