Metadata-Version: 2.1
Name: wsblib
Version: 1.0.0
Summary: Base library for other web servers.
Home-page: https://github.com/firlast/wsblib
Author: Jaedson Silva
Author-email: imunknowuser@protonmail.com
License: UNKNOWN
Project-URL: License, https://github.com/firlast/wsblib/blob/master/LICENSE
Keywords: www,http,server,internet,socket
Platform: UNKNOWN
Classifier: License :: OSI Approved :: BSD License
Classifier: Development Status :: 5 - Production/Stable
Classifier: Intended Audience :: Developers
Classifier: Natural Language :: English
Classifier: Operating System :: OS Independent
Classifier: Programming Language :: Python :: 3
Classifier: Topic :: Internet :: WWW/HTTP :: HTTP Servers
Classifier: Topic :: Internet :: WWW/HTTP :: WSGI
